cloudfoundryclient/__init__.py
cloudfoundryclient/common/__init__.py
cloudfoundryclient/common/exceptions.py
cloudfoundryclient/tests/base.py
cloudfoundryclient/tests/test_cloudfoundryclient.py
cloudfoundryclient/tests/__init__.py
cloudfoundryclient/v2/__init__.py
cloudfoundryclient/v2/client.py
python_cloudfoundryclient-1.0.2.dist-info/WHEEL
python_cloudfoundryclient-1.0.2.dist-info/metadata.json
python_cloudfoundryclient-1.0.2.dist-info/METADATA
python_cloudfoundryclient-1.0.2.dist-info/RECORD
python_cloudfoundryclient-1.0.2.dist-info/DESCRIPTION.rst
python_cloudfoundryclient-1.0.2.dist-info/pbr.json
python_cloudfoundryclient-1.0.2.dist-info/top_level.txt
